pydseamslib/__init__.py
pydseamslib/cyoda.cpython-312-x86_64-linux-gnu.so
pydseamslib/adapters/__init__.py
pydseamslib/adapters/_ase.py
pydseamslib-0.0.2.dist-info/WHEEL
pydseamslib-0.0.2.dist-info/METADATA
pydseamslib-0.0.2.dist-info/RECORD
